Metadata-Version: 2.3
Name: elyra-server
Version: 4.0.0
Summary: The elyra-server package provides common core libraries and functions that are required by Elyra's individual extensions. Note: Installing this package alone will not enable the use of Elyra. Please install the 'elyra' package instead. e.g. pip install elyra[all]
Project-URL: Documentation, https://elyra.readthedocs.io/en/latest
Project-URL: Homepage, https://github.com/elyra-ai/elyra
Maintainer: Elyra Maintainers
Classifier: License :: OSI Approved :: Apache Software License
Classifier: Operating System :: OS Independent
Classifier: Programming Language :: Python :: 3.9
Classifier: Programming Language :: Python :: 3.10
Classifier: Programming Language :: Python :: 3.11
Classifier: Programming Language :: Python :: 3.12
Classifier: Programming Language :: Python :: 3.13
Classifier: Topic :: Scientific/Engineering
Classifier: Topic :: Scientific/Engineering :: Artificial Intelligence
Classifier: Topic :: Software Development
Classifier: Topic :: Software Development :: Libraries
Classifier: Topic :: Software Development :: Libraries :: Python Modules
Requires-Python: >=3.9
Requires-Dist: appengine-python-standard
Requires-Dist: autopep8>=1.5.0
Requires-Dist: black>=22.8.0
Requires-Dist: click==8.1.8
Requires-Dist: colorama
Requires-Dist: deprecation
Requires-Dist: entrypoints>=0.3
Requires-Dist: jinja2>=3
Requires-Dist: jsonschema>=3.2.0
Requires-Dist: jupyter-client>=7.4.9
Requires-Dist: jupyter-core>=5.3.1
Requires-Dist: jupyter-events>=0.7.0
Requires-Dist: jupyter-packaging>=0.12.3
Requires-Dist: jupyter-resource-usage~=1.1.0
Requires-Dist: jupyter-server>=2.7.3
Requires-Dist: jupyterlab-git~=0.51.2
Requires-Dist: jupyterlab-lsp~=5.1.0
Requires-Dist: jupyterlab~=4.4
Requires-Dist: markupsafe>=2.1
Requires-Dist: minio!=7.2.1,>=7.0.0
Requires-Dist: nbclient>=0.10.0
Requires-Dist: nbconvert>=6.5.1
Requires-Dist: nbdime~=4.0.1
Requires-Dist: nbformat>=5.1.2
Requires-Dist: networkx>=2.5.1
Requires-Dist: papermill>=2.3.4
Requires-Dist: pygithub
Requires-Dist: python-lsp-server[all]>=1.11.0
Requires-Dist: pyyaml>=5.3.1
Requires-Dist: requests>=2.31
Requires-Dist: rfc3986-validator>=0.1.1
Requires-Dist: tornado>=6.1.0
Requires-Dist: traitlets>=4.3.2
Requires-Dist: typing-extensions>=3.10
Requires-Dist: urllib3>=1.26.5
Requires-Dist: watchdog>=2.1.3
Requires-Dist: websocket-client
Requires-Dist: yaspin
Provides-Extra: airflow
Provides-Extra: airflow-gitlab
Requires-Dist: python-gitlab; extra == 'airflow-gitlab'
Provides-Extra: all
Requires-Dist: elyra-examples-kfp-catalog; extra == 'all'
Requires-Dist: kfp!=1.7.2,<2.0,>=1.7.0; extra == 'all'
Requires-Dist: kfp-tekton>=1.5.2; extra == 'all'
Requires-Dist: python-gitlab; extra == 'all'
Requires-Dist: typing-extensions<5,>=3.10; extra == 'all'
Provides-Extra: kfp
Requires-Dist: kfp!=1.7.2,<2.0,>=1.7.0; extra == 'kfp'
Requires-Dist: mistune<3.1.0; extra == 'kfp'
Requires-Dist: typing-extensions<5,>=3.10; extra == 'kfp'
Provides-Extra: kfp-examples
Requires-Dist: elyra-examples-kfp-catalog; extra == 'kfp-examples'
Provides-Extra: kfp-tekton
Requires-Dist: kfp-tekton>=1.5.2; extra == 'kfp-tekton'
Requires-Dist: mistune<3.1.0; extra == 'kfp-tekton'
Provides-Extra: test
Requires-Dist: elyra-examples-kfp-catalog; extra == 'test'
Requires-Dist: git-python; extra == 'test'
Requires-Dist: importlib-resources; extra == 'test'
Requires-Dist: kfp-tekton; extra == 'test'
Requires-Dist: pytest-console-scripts; extra == 'test'
Requires-Dist: pytest-cov; extra == 'test'
Requires-Dist: pytest-jupyter; extra == 'test'
Requires-Dist: pytest-tornasync; extra == 'test'
Requires-Dist: pytest-virtualenv; extra == 'test'
Requires-Dist: pytest>=5.4.1; extra == 'test'
Requires-Dist: requests-mock; extra == 'test'
Requires-Dist: requests-unixsocket; extra == 'test'
